{
	"envs":	[
				{
					"env_id":1,
					"env_name":"MiniGrid-DoorKey",
					"initial_state":0,
          "n_rm_states":4,
					"rm_states": [
									{"u1":0, "u2":0, "delta_u":"!k", "delta_r": "ConstantRewardFunction(0)"},
									{"u1":0, "u2":1, "delta_u":"k", "delta_r": "ConstantRewardFunction(0)"},
									{"u1":1, "u2":0, "delta_u":"!k", "delta_r": "ConstantRewardFunction(0)"},
									{"u1":1, "u2":1, "delta_u":"k&!o", "delta_r": "ConstantRewardFunction(0)"},
									{"u1":1, "u2":2, "delta_u":"o", "delta_r": "ConstantRewardFunction(0)"},
									{"u1":2, "u2":2, "delta_u":"!g", "delta_r": "ConstantRewardFunction(0)"},
									{"u1":2, "u2":3, "delta_u":"g", "delta_r": "ConstantRewardFunction(1)"},
									{"u1":3, "u2":3, "delta_u":"True", "delta_r": "ConstantRewardFunction(0)"}
								]
				},
				{
					"env_id":2,
					"env_name":"MiniGrid-Unlock",
					"initial_state":0,
          "n_rm_states":3,
					"rm_states": [
									{"u1":0, "u2":0, "delta_u":"!k", "delta_r": "ConstantRewardFunction(0)"},
									{"u1":0, "u2":1, "delta_u":"k", "delta_r": "ConstantRewardFunction(0)"},
									{"u1":1, "u2":1, "delta_u":"k&!o", "delta_r": "ConstantRewardFunction(0)"},
									{"u1":1, "u2":0, "delta_u":"!k&!o", "delta_r": "ConstantRewardFunction(0)"},
									{"u1":1, "u2":2, "delta_u":"k&o", "delta_r": "ConstantRewardFunction(1)"},
									{"u1":2, "u2":2, "delta_u":"True", "delta_r": "ConstantRewardFunction(0)"}
								]
				},
				{
					"env_id":3,
					"env_name":"MiniGrid-Empty",
					"initial_state":0,
          "n_rm_states":2,
					"rm_states": [
									{"u1":0, "u2":0, "delta_u":"!g", "delta_r": "ConstantRewardFunction(0)"},
									{"u1":0, "u2":1, "delta_u":"g", "delta_r": "ConstantRewardFunction(1)"},
									{"u1":1, "u2":1, "delta_u":"True", "delta_r": "ConstantRewardFunction(0)"}
								]
				},
	            {
					"env_id":4,
					"env_name":"MiniGrid-KeyCorridorS3R1",
					"initial_state":0,
                    "n_rm_states":4,
					"rm_states": [
									{"u1":0, "u2":0, "delta_u":"!k", "delta_r": "ConstantRewardFunction(0)"},
									{"u1":0, "u2":1, "delta_u":"k", "delta_r": "ConstantRewardFunction(0)"},
									{"u1":1, "u2":0, "delta_u":"!k", "delta_r": "ConstantRewardFunction(0)"},
									{"u1":1, "u2":1, "delta_u":"k&!o", "delta_r": "ConstantRewardFunction(0)"},
									{"u1":1, "u2":2, "delta_u":"o", "delta_r": "ConstantRewardFunction(0)"},
									{"u1":2, "u2":2, "delta_u":"!g", "delta_r": "ConstantRewardFunction(0)"},
									{"u1":2, "u2":3, "delta_u":"g", "delta_r": "ConstantRewardFunction(1)"},
									{"u1":3, "u2":3, "delta_u":"True", "delta_r": "ConstantRewardFunction(0)"}
								]
				},
                {
					"env_id":5,
					"env_name":"MiniGrid-KeyCorridorS3R2",
					"initial_state":0,
                    "n_rm_states":4,
					"rm_states": [
									{"u1":0, "u2":0, "delta_u":"!k", "delta_r": "ConstantRewardFunction(0)"},
									{"u1":0, "u2":1, "delta_u":"k", "delta_r": "ConstantRewardFunction(0)"},
									{"u1":1, "u2":0, "delta_u":"!k", "delta_r": "ConstantRewardFunction(0)"},
									{"u1":1, "u2":1, "delta_u":"k&!o", "delta_r": "ConstantRewardFunction(0)"},
									{"u1":1, "u2":2, "delta_u":"o", "delta_r": "ConstantRewardFunction(0)"},
									{"u1":2, "u2":2, "delta_u":"!g", "delta_r": "ConstantRewardFunction(0)"},
									{"u1":2, "u2":3, "delta_u":"g", "delta_r": "ConstantRewardFunction(1)"},
									{"u1":3, "u2":3, "delta_u":"True", "delta_r": "ConstantRewardFunction(0)"}
								]
				},

                {
					"env_id":6,
					"env_name":"MiniGrid-KeyCorridorS3R3",
					"initial_state":0,
                    "n_rm_states":4,
					"rm_states": [
									{"u1":0, "u2":0, "delta_u":"!k", "delta_r": "ConstantRewardFunction(0)"},
									{"u1":0, "u2":1, "delta_u":"k", "delta_r": "ConstantRewardFunction(0)"},
									{"u1":1, "u2":0, "delta_u":"!k", "delta_r": "ConstantRewardFunction(0)"},
									{"u1":1, "u2":1, "delta_u":"k&!o", "delta_r": "ConstantRewardFunction(0)"},
									{"u1":1, "u2":2, "delta_u":"o", "delta_r": "ConstantRewardFunction(0)"},
									{"u1":2, "u2":2, "delta_u":"!g", "delta_r": "ConstantRewardFunction(0)"},
									{"u1":2, "u2":3, "delta_u":"g", "delta_r": "ConstantRewardFunction(1)"},
									{"u1":3, "u2":3, "delta_u":"True", "delta_r": "ConstantRewardFunction(0)"}
								]
				},

                {
					"env_id":7,
					"env_name":"MiniGrid-KeyCorridorS4R3",
					"initial_state":0,
                    "n_rm_states":4,
					"rm_states": [
									{"u1":0, "u2":0, "delta_u":"!k", "delta_r": "ConstantRewardFunction(0)"},
									{"u1":0, "u2":1, "delta_u":"k", "delta_r": "ConstantRewardFunction(0)"},
									{"u1":1, "u2":0, "delta_u":"!k", "delta_r": "ConstantRewardFunction(0)"},
									{"u1":1, "u2":1, "delta_u":"k&!o", "delta_r": "ConstantRewardFunction(0)"},
									{"u1":1, "u2":2, "delta_u":"o", "delta_r": "ConstantRewardFunction(0)"},
									{"u1":2, "u2":2, "delta_u":"!g", "delta_r": "ConstantRewardFunction(0)"},
									{"u1":2, "u2":3, "delta_u":"g", "delta_r": "ConstantRewardFunction(1)"},
									{"u1":3, "u2":3, "delta_u":"True", "delta_r": "ConstantRewardFunction(0)"}
								]
				}

				]
}